LICENSE
MANIFEST.in
README.rst
setup.cfg
setup.py
wagtail_modelchooser_1.13.1.egg-info/PKG-INFO
wagtail_modelchooser_1.13.1.egg-info/SOURCES.txt
wagtail_modelchooser_1.13.1.egg-info/dependency_links.txt
wagtail_modelchooser_1.13.1.egg-info/not-zip-safe
wagtail_modelchooser_1.13.1.egg-info/requires.txt
wagtail_modelchooser_1.13.1.egg-info/top_level.txt
wagtailmodelchooser/__init__.py
wagtailmodelchooser/blocks.py
wagtailmodelchooser/edit_handlers.py
wagtailmodelchooser/urls.py
wagtailmodelchooser/utils.py
wagtailmodelchooser/version.py
wagtailmodelchooser/views.py
wagtailmodelchooser/wagtail_hooks.py
wagtailmodelchooser/widgets.py
wagtailmodelchooser/static/wagtailmodelchooser/js/model_chooser.js
wagtailmodelchooser/templates/wagtailmodelchooser/modal.html
wagtailmodelchooser/templates/wagtailmodelchooser/modal.js
wagtailmodelchooser/templates/wagtailmodelchooser/model_chooser.html
wagtailmodelchooser/templates/wagtailmodelchooser/results.html